totoon/__init__.py
totoon/converters.py
totoon/core.py
totoon-0.1.1.dist-info/licenses/LICENSE
totoon-0.1.1.dist-info/METADATA
totoon-0.1.1.dist-info/WHEEL
totoon-0.1.1.dist-info/top_level.txt
totoon-0.1.1.dist-info/RECORD
