Metadata-Version: 2.4
Name: totoon
Version: 0.1.1
Summary: Convert any data format to TOON (Token-Oriented Object Notation)
Author-email: totoon <contact@totoon.dev>
License-Expression: MIT
Project-URL: Homepage, https://github.com/bug4fix/totoon
Project-URL: Documentation, https://github.com/bug4fix/totoon#readme
Project-URL: Repository, https://github.com/bug4fix/totoon
Project-URL: Issues, https://github.com/bug4fix/totoon/issues
Keywords: toon,json,llm,data-format,converter
Classifier: Development Status :: 3 - Alpha
Classifier: Intended Audience :: Developers
Classifier: Programming Language :: Python :: 3
Classifier: Programming Language :: Python :: 3.8
Classifier: Programming Language :: Python :: 3.9
Classifier: Programming Language :: Python :: 3.10
Classifier: Programming Language :: Python :: 3.11
Classifier: Programming Language :: Python :: 3.12
Classifier: Topic :: Software Development :: Libraries :: Python Modules
Classifier: Topic :: Text Processing :: Markup
Requires-Python: >=3.8
License-File: LICENSE
Requires-Dist: pyyaml>=6.0
Provides-Extra: dev
Requires-Dist: pytest>=7.0; extra == "dev"
Requires-Dist: pytest-cov>=4.0; extra == "dev"
Requires-Dist: black>=23.0; extra == "dev"
Requires-Dist: ruff>=0.1.0; extra == "dev"
Provides-Extra: publish
Requires-Dist: build>=0.10.0; extra == "publish"
Requires-Dist: twine>=4.0.0; extra == "publish"
Dynamic: license-file
